{"v":4,"entries":{"components-button--docs":{"id":"components-button--docs","title":"Components/Button","name":"Docs","importPath":"./stories/Button.stories.tsx","type":"docs","tags":["docs","autodocs"],"storiesImports":[]},"components-button--default":{"id":"components-button--default","title":"Components/Button","name":"Default","importPath":"./stories/Button.stories.tsx","tags":["story"],"type":"story"},"components-button--nhm":{"id":"components-button--nhm","title":"Components/Button","name":"NHM","importPath":"./stories/Button.stories.tsx","tags":["story"],"type":"story"},"components-button--lbtp":{"id":"components-button--lbtp","title":"Components/Button","name":"LBTP","importPath":"./stories/Button.stories.tsx","tags":["story"],"type":"story"},"components-button--destructive":{"id":"components-button--destructive","title":"Components/Button","name":"Destructive","importPath":"./stories/Button.stories.tsx","tags":["story"],"type":"story"},"components-cart--docs":{"id":"components-cart--docs","title":"Components/Cart","name":"Docs","importPath":"./stories/Cart.stories.tsx","type":"docs","tags":["docs","autodocs"],"storiesImports":[]},"components-cart--default":{"id":"components-cart--default","title":"Components/Cart","name":"Default","importPath":"./stories/Cart.stories.tsx","tags":["story"],"type":"story"},"components-forms-checkbox--docs":{"id":"components-forms-checkbox--docs","title":"Components/Forms/Checkbox","name":"Docs","importPath":"./stories/Checkbox.stories.tsx","type":"docs","tags":["docs","autodocs"],"storiesImports":[]},"components-forms-checkbox--default":{"id":"components-forms-checkbox--default","title":"Components/Forms/Checkbox","name":"Default","importPath":"./stories/Checkbox.stories.tsx","tags":["story"],"type":"story"},"components-forms-checkboxgroup--docs":{"id":"components-forms-checkboxgroup--docs","title":"Components/Forms/CheckboxGroup","name":"Docs","importPath":"./stories/CheckboxGroup.stories.tsx","type":"docs","tags":["docs","autodocs"],"storiesImports":[]},"components-forms-checkboxgroup--default":{"id":"components-forms-checkboxgroup--default","title":"Components/Forms/CheckboxGroup","name":"Default","importPath":"./stories/CheckboxGroup.stories.tsx","tags":["story"],"type":"story"},"components-counter--docs":{"id":"components-counter--docs","title":"Components/Counter","name":"Docs","importPath":"./stories/Counter.stories.tsx","type":"docs","tags":["docs","autodocs"],"storiesImports":[]},"components-counter--default":{"id":"components-counter--default","title":"Components/Counter","name":"Default","importPath":"./stories/Counter.stories.tsx","tags":["story"],"type":"story"},"components-forms-form--docs":{"id":"components-forms-form--docs","title":"Components/Forms/Form","name":"Docs","importPath":"./stories/Form.stories.tsx","type":"docs","tags":["docs","autodocs"],"storiesImports":[]},"components-forms-form--default":{"id":"components-forms-form--default","title":"Components/Forms/Form","name":"Default","importPath":"./stories/Form.stories.tsx","tags":["story"],"type":"story"},"components-forms-input--docs":{"id":"components-forms-input--docs","title":"Components/Forms/Input","name":"Docs","importPath":"./stories/Input.stories.tsx","type":"docs","tags":["docs","autodocs"],"storiesImports":[]},"components-forms-input--default":{"id":"components-forms-input--default","title":"Components/Forms/Input","name":"Default","importPath":"./stories/Input.stories.tsx","tags":["story"],"type":"story"},"components-forms-input--disabled":{"id":"components-forms-input--disabled","title":"Components/Forms/Input","name":"Disabled","importPath":"./stories/Input.stories.tsx","tags":["story"],"type":"story"},"components-forms-input--required":{"id":"components-forms-input--required","title":"Components/Forms/Input","name":"Required","importPath":"./stories/Input.stories.tsx","tags":["story"],"type":"story"},"components-forms-inputgroup--docs":{"id":"components-forms-inputgroup--docs","title":"Components/Forms/InputGroup","name":"Docs","importPath":"./stories/InputGroup.stories.tsx","type":"docs","tags":["docs","autodocs"],"storiesImports":[]},"components-forms-inputgroup--default":{"id":"components-forms-inputgroup--default","title":"Components/Forms/InputGroup","name":"Default","importPath":"./stories/InputGroup.stories.tsx","tags":["story"],"type":"story"},"components-photocallout--docs":{"id":"components-photocallout--docs","title":"Components/PhotoCallout","name":"Docs","importPath":"./stories/PhotoCallout.stories.tsx","type":"docs","tags":["docs","autodocs"],"storiesImports":[]},"components-photocallout--default":{"id":"components-photocallout--default","title":"Components/PhotoCallout","name":"Default","importPath":"./stories/PhotoCallout.stories.tsx","tags":["story"],"type":"story"},"components-forms-radio--docs":{"id":"components-forms-radio--docs","title":"Components/Forms/Radio","name":"Docs","importPath":"./stories/Radio.stories.tsx","type":"docs","tags":["docs","autodocs"],"storiesImports":[]},"components-forms-radio--default":{"id":"components-forms-radio--default","title":"Components/Forms/Radio","name":"Default","importPath":"./stories/Radio.stories.tsx","tags":["story"],"type":"story"},"components-forms-radiogroup--docs":{"id":"components-forms-radiogroup--docs","title":"Components/Forms/RadioGroup","name":"Docs","importPath":"./stories/RadioGroup.stories.tsx","type":"docs","tags":["docs","autodocs"],"storiesImports":[]},"components-forms-radiogroup--default":{"id":"components-forms-radiogroup--default","title":"Components/Forms/RadioGroup","name":"Default","importPath":"./stories/RadioGroup.stories.tsx","tags":["story"],"type":"story"},"components-forms-select--docs":{"id":"components-forms-select--docs","title":"Components/Forms/Select","name":"Docs","importPath":"./stories/Select.stories.tsx","type":"docs","tags":["docs","autodocs"],"storiesImports":[]},"components-forms-select--default":{"id":"components-forms-select--default","title":"Components/Forms/Select","name":"Default","importPath":"./stories/Select.stories.tsx","tags":["story"],"type":"story"},"atoms-text--docs":{"id":"atoms-text--docs","title":"Atoms/Text","name":"Docs","importPath":"./stories/Text.stories.tsx","type":"docs","tags":["docs","autodocs"],"storiesImports":[]},"atoms-text--text":{"id":"atoms-text--text","title":"Atoms/Text","name":"Text","importPath":"./stories/Text.stories.tsx","tags":["story"],"type":"story"},"components-forms-textarea--docs":{"id":"components-forms-textarea--docs","title":"Components/Forms/TextArea","name":"Docs","importPath":"./stories/TextArea.stories.tsx","type":"docs","tags":["docs","autodocs"],"storiesImports":[]},"components-forms-textarea--default":{"id":"components-forms-textarea--default","title":"Components/Forms/TextArea","name":"Default","importPath":"./stories/TextArea.stories.tsx","tags":["story"],"type":"story"},"components-ticketrow--docs":{"id":"components-ticketrow--docs","title":"Components/TicketRow","name":"Docs","importPath":"./stories/TicketRow.stories.tsx","type":"docs","tags":["docs","autodocs"],"storiesImports":[]},"components-ticketrow--default":{"id":"components-ticketrow--default","title":"Components/TicketRow","name":"Default","importPath":"./stories/TicketRow.stories.tsx","tags":["story"],"type":"story"}}}
